pepfeature/__init__.py
pepfeature/_test.py
pepfeature/_utils.py
pepfeature/aa_CT.py
pepfeature/aa_all_feat.py
pepfeature/aa_composition.py
pepfeature/aa_descriptors.py
pepfeature/aa_kmer_composition.py
pepfeature/aa_molecular_weight.py
pepfeature/aa_num_of_atoms.py
pepfeature/aa_proportion.py
pepfeature/aa_seq_entropy.py
pepfeature/data/AAdescriptors.xlsx
pepfeature/data/Model_Data.csv
pepfeature/data/Sample_Data.csv
Pepfeature-1.0.10.dist-info/METADATA
Pepfeature-1.0.10.dist-info/WHEEL
Pepfeature-1.0.10.dist-info/top_level.txt
Pepfeature-1.0.10.dist-info/RECORD
