Metadata-Version: 2.1
Name: Pepfeature
Version: 1.0.10
Summary: A package that consists of functions for calculating epitope/peptide features for prediction purposes (Feature calculation/extraction)
Home-page: https://github.com/essakh/pepfeature
Author: Essa Khan
Author-email: contact.essakh@gmail.com
License: MIT
Platform: UNKNOWN
Classifier: License :: OSI Approved :: MIT License
Classifier: Programming Language :: Python :: 3
Classifier: Programming Language :: Python :: 3.8
Requires-Dist: et-xmlfile (>=1.1.0)
Requires-Dist: numpy (>=1.20.2)
Requires-Dist: openpyxl (>=3.0.7)
Requires-Dist: pandas (>=1.2.4)
Requires-Dist: setuptools (>=56.0.0)
Requires-Dist: python-dateutil (>=2.8.1)
Requires-Dist: pytz (>=2021.1)
Requires-Dist: six (>=1.15.0)
